{
  "events": {
    {
      "event": "1",
      "title": "Событие 1",
      "date": "2019-12-1",
      "previewText": "Красткое описание мероприятия",
      "location": "Место проведения мероприятия",
      "allday": true,
      "type": null,
      "placeevent": null,
      "placeName": "",
    }, {
      "event": "2",
      "title": "Событие 2",
      "date": "2019-12-2",
      "previewText": "Красткое описание мероприятия",
      "location": "Место проведения мероприятия",
      "allday": true,
      "type": null,
      "placeevent": null,
      "placeName": "",
    }, {
      "event": "3",
      "title": "Событие 3",
      "date": "2019-12-3",
      "previewText": "Красткое описание мероприятия",
      "location": "Место проведения мероприятия",
      "allday": true,
      "type": null,
      "placeevent": null,
      "placeName": "",
    }, {
      "event": "4",
      "title": "Событие 4",
      "date": "2019-12-4",
      "previewText": "Красткое описание мероприятия",
      "location": "Место проведения мероприятия",
      "allday": true,
      "type": null,
      "placeevent": null,
      "placeName": "",
    }, {
      "event": "5",
      "title": "Событие 5",
      "date": "2019-12-5",
      "previewText": "Красткое описание мероприятия",
      "location": "Место проведения мероприятия",
      "allday": true,
      "type": null,
      "placeevent": null,
      "placeName": "",
    }, {
      "event": "6",
      "title": "Событие 6",
      "date": "2019-12-6",
      "previewText": "Красткое описание мероприятия",
      "location": "Место проведения мероприятия",
      "allday": true,
      "type": null,
      "placeevent": null,
      "placeName": "",
    }, {
      "event": "7",
      "title": "Событие 7",
      "date": "2019-12-7",
      "previewText": "Красткое описание мероприятия",
      "location": "Место проведения мероприятия",
      "allday": true,
      "type": null,
      "placeevent": null,
      "placeName": "",
    }
  }
}
